pyaubo_sdk.cp310-win_amd64.pyd
pyaubo_sdk.cp310-win_amd64.pyd.manifest
pyaubo_sdk-0.24.1.dist-info/METADATA
pyaubo_sdk-0.24.1.dist-info/WHEEL
pyaubo_sdk-0.24.1.dist-info/top_level.txt
pyaubo_sdk-0.24.1.dist-info/RECORD
