Metadata-Version: 2.1
Name: pyaubo-sdk
Version: 0.24.1
Summary: A Python interface for controlling aubo robot 
Classifier: Programming Language :: Python :: 3
Classifier: License :: OSI Approved :: MIT License
Requires-Python: >=3.6, <=3.12
